zapmyco/config.py
zapmyco/integrations/__init__.py
zapmyco/integrations/home_assistant/__init__.py
zapmyco/integrations/home_assistant/main.py
zapmyco/integrations/home_assistant/models.py
zapmyco/llm.py
zapmyco/main.py
zapmyco/mcp_client.py
zapmyco/mcp_servers/home_assistant.py
zapmyco/models/device.py
zapmyco/models/preference.py
zapmyco/models/user.py
zapmyco/security/authentication.py
zapmyco/security/encryption.py
zapmyco/security/privacy.py
zapmyco/utils/config_manager.py
zapmyco/utils/helpers.py
zapmyco/utils/logger.py
zapmyco/voice.py
zapmyco-0.1.1.dist-info/LICENSE
zapmyco-0.1.1.dist-info/METADATA
zapmyco-0.1.1.dist-info/WHEEL
zapmyco-0.1.1.dist-info/RECORD
