Metadata-Version: 2.3
Name: zapmyco
Version: 0.1.1
Summary: Zapmyco is a home agent.
License: Apache-2.0
Author: shenjingnan
Author-email: sjn.code@gmail.com
Requires-Python: >=3.13.0,<3.14
Classifier: License :: OSI Approved :: Apache Software License
Classifier: Programming Language :: Python :: 3
Classifier: Programming Language :: Python :: 3.13
Requires-Dist: accelerate (>=1.6.0,<2.0.0)
Requires-Dist: aiohttp (>=3.11.16,<4.0.0)
Requires-Dist: async-timeout (>=5.0.1,<6.0.0)
Requires-Dist: black (>=24.2.0,<25.0.0)
Requires-Dist: chromadb[all] (>=1.0.4,<2.0.0)
Requires-Dist: cryptography (>=44.0.1,<45.0.0)
Requires-Dist: dashscope (>=1.23.1,<2.0.0)
Requires-Dist: datetime (>=5.5,<6.0)
Requires-Dist: httpx[socks] (>=0.28.1,<0.29.0)
Requires-Dist: jieba (>=0.42.1,<0.43.0)
Requires-Dist: jsonschema (>=4.23.0,<5.0.0)
Requires-Dist: levenshtein (>=0.27.1,<0.28.0)
Requires-Dist: librosa (>=0.11.0,<0.12.0)
Requires-Dist: mcp (>=1.6.0,<2.0.0)
Requires-Dist: numpy (>=2.2.4,<3.0.0)
Requires-Dist: openai (>=1.70.0,<2.0.0)
Requires-Dist: pandas (>=2.2.3,<3.0.0)
Requires-Dist: pyaudio (>=0.2.14,<0.3.0)
Requires-Dist: pydub (>=0.25.1,<0.26.0)
Requires-Dist: pylint (>=3.3.6,<4.0.0)
Requires-Dist: python-dotenv (>=1.0.1,<2.0.0)
Requires-Dist: pyttsx3 (>=2.98,<3.0)
Requires-Dist: pyyaml (>=6.0.2,<7.0.0)
Requires-Dist: soundfile (>=0.13.1,<0.14.0)
Requires-Dist: torch (>=2.6.0,<3.0.0)
Requires-Dist: transformers (>=4.51.0,<5.0.0)
Requires-Dist: websockets (>=12.0,<13.0)
Project-URL: Repository, https://github.com/zapmyco/zapmyco
